MANIFEST.in
README.md
development.ini
production.ini
setup.py
webNUT.egg-info/PKG-INFO
webNUT.egg-info/SOURCES.txt
webNUT.egg-info/dependency_links.txt
webNUT.egg-info/entry_points.txt
webNUT.egg-info/not-zip-safe
webNUT.egg-info/requires.txt
webNUT.egg-info/top_level.txt
webnut/__init__.py
webnut/config.example.py
webnut/config.py
webnut/views.py
webnut/webnut.py
webnut/templates/404.pt
webnut/templates/index.pt
webnut/templates/layout.pt
webnut/templates/ups_view.pt