Metadata-Version: 1.1
Name: webNUT
Version: 0.0.1
Summary: webNUT
Home-page: https://github.com/rshipp/webNUT
Author: rshipp
Author-email: python@rshipp.com
License: UNKNOWN
Keywords: web pyramid pylons nut network ups tools
Platform: UNKNOWN
Classifier: Programming Language :: Python
Classifier: Framework :: Pyramid
Classifier: Topic :: Internet :: WWW/HTTP
Classifier: Topic :: Internet :: WWW/HTTP :: WSGI :: Application
Classifier: Topic :: System :: Power (UPS)
